odoo9_addon_purchase_variant_configurator_on_confirm-9.0.1.0.0-py2.7-nspkg.pth
odoo9_addon_purchase_variant_configurator_on_confirm-9.0.1.0.0.dist-info/top_level.txt
odoo9_addon_purchase_variant_configurator_on_confirm-9.0.1.0.0.dist-info/WHEEL
odoo9_addon_purchase_variant_configurator_on_confirm-9.0.1.0.0.dist-info/RECORD
odoo9_addon_purchase_variant_configurator_on_confirm-9.0.1.0.0.dist-info/metadata.json
odoo9_addon_purchase_variant_configurator_on_confirm-9.0.1.0.0.dist-info/DESCRIPTION.rst
odoo9_addon_purchase_variant_configurator_on_confirm-9.0.1.0.0.dist-info/METADATA
odoo9_addon_purchase_variant_configurator_on_confirm-9.0.1.0.0.dist-info/namespace_packages.txt
odoo_addons/purchase_variant_configurator_on_confirm/__openerp__.py
odoo_addons/purchase_variant_configurator_on_confirm/__init__.py
odoo_addons/purchase_variant_configurator_on_confirm/README.rst
odoo_addons/purchase_variant_configurator_on_confirm/models/product_template.py
odoo_addons/purchase_variant_configurator_on_confirm/models/purchase_order.py
odoo_addons/purchase_variant_configurator_on_confirm/models/__init__.py
odoo_addons/purchase_variant_configurator_on_confirm/models/purchase_order_line.py
odoo_addons/purchase_variant_configurator_on_confirm/views/inherited_purchase_order_views.xml
odoo_addons/purchase_variant_configurator_on_confirm/static/description/icon.png
