Metadata-Version: 2.0
Name: odoo9-addon-purchase-variant-configurator-on-confirm
Version: 9.0.1.0.0
Summary: Create product variants when confirming the purchase order
Home-page: https://odoo-community.org/
Author: OdooMRP team, AvanzOSC, Tecnativa, Serv. Tecnol. Avanzados - Pedro M. Baeza,ACSONE SA/NV,Odoo Community Association (OCA)
Author-email: support@odoo-community.org
License: AGPL-3
Platform: UNKNOWN
Requires-Dist: odoo (<9.1a,>=9.0a)
Requires-Dist: odoo9-addon-purchase-variant-configurator
Classifier: Programming Language :: Python :: 2.7
Classifier: Framework :: Odoo
Classifier: License :: OSI Approved :: GNU Affero General Public License v3
